{
  "source": "36氪",
  "source_url": "https://www.36kr.com/feed",
  "fetch_time": "2026-07-01T08:11:31.062Z",
  "articles": [
    {
      "title": "横店东磁：目前没有太空光伏产品",
      "date": "Wed, 01 Jul 2026 08:08:23 GMT",
      "summary": "36氪获悉，横店东磁在互动平台表示，公司现有光伏产品面向地面应用，目前没有太空光伏产品。",
      "url": "https://36kr.com/newsflashes/3876803434491909?f=rss",
      "category": ""
    },
    {
      "title": "现代汽车6月全球销量同比减少5.9%",
      "date": "Wed, 01 Jul 2026 08:02:40 GMT",
      "summary": "7月1日，韩国汽车制造商现代汽车公布，2026年6月全球销量为338,313辆，同比减少5.9%。其中，国内市场销量为58,232辆，同比减少6.2%；海外市场销量280,081辆，同比减少5.8%。（界面）",
      "url": "https://36kr.com/newsflashes/3876797812453384?f=rss",
      "category": ""
    },
    {
      "title": "中昊芯英正式发布新一代高性能TPU AI专用算力芯片“须臾®”",
      "date": "Wed, 01 Jul 2026 08:01:29 GMT",
      "summary": "36氪获悉，中昊芯英近日正式发布新一代全自研高性能TPU AI专用算力芯片“须臾®”，同步推出搭载“须臾®”芯片构建的软硬件一体化智算底座泰则®2.0 AI高性能智算平台。目前，公司产品已成功部署于由深圳联通、天津移动、太极股份、江西上饶等运营商、政府机构、及科技企业建设的多个超大规模智算中心，并已在高校、科研机构等的科研计算平台与教学实验环境中投入使用。",
      "url": "https://36kr.com/newsflashes/3876796652253442?f=rss",
      "category": ""
    },
    {
      "title": "中科飞测：子公司收到702万元政府补助款",
      "date": "Wed, 01 Jul 2026 07:54:10 GMT",
      "summary": "36氪获悉，中科飞测公告，公司全资子公司飞测思凯浦（上海）半导体科技有限公司于近日收到702万元的政府补助款，预计对公司2026年度的利润产生一定的积极影响。",
      "url": "https://36kr.com/newsflashes/3876789467033606?f=rss",
      "category": ""
    },
    {
      "title": "小米人事调整：中国区总裁王晓雁不再兼任销售运营一部总经理，陈幕楠接任",
      "date": "Wed, 01 Jul 2026 07:47:21 GMT",
      "summary": "小米中国区近日迎来人事调整，涉及汽车销交服部、销售运营一部、电商部、新零售部等多个部门。其中，任命樊家麟担任汽车销交服部下辖的销售运营部代理总经理，向汽车销交服部总经理夏志国汇报。任命陈幕楠担任销售运营一部总经理，向集团高级副总裁、中国区总裁王晓雁汇报。任命新零售部总经理张健兼任小米之家总经理，原小米之家总经理陈恺则担任电商部总经理，向集团高级副总裁、中国区总裁王晓雁汇报。（新浪科技）",
      "url": "https://36kr.com/newsflashes/3876782765453315?f=rss",
      "category": ""
    },
    {
      "title": "西门子将在德国投资3亿欧元，扩大用于AI数据中心等的技术产能",
      "date": "Wed, 01 Jul 2026 07:42:24 GMT",
      "summary": "西门子7月1日宣布将在德国投资3亿欧元，大幅扩大用于全球能源转型及AI数据中心的关键技术产能。投资项目包括在德国奥芬巴赫新建一处供应商设施，以及扩建位于法兰克福的两家现有工厂。工程将于今年7月动工，供应商设施预计于2027年春季投产。该投资项目将在2030年底前创造700个新的就业岗位。（界面）",
      "url": "https://36kr.com/newsflashes/3876777898979593?f=rss",
      "category": ""
    }
  ],
  "status": "success",
  "error": null
}