{
  "source": "36氪",
  "source_url": "https://www.36kr.com/feed",
  "fetch_time": "2026-05-11T07:39:18.324Z",
  "articles": [
    {
      "title": "飞凯材料：公司半导体材料可用于PLP封装，但目前营收规模不大",
      "date": "Mon, 11 May 2026 07:35:10 GMT",
      "summary": "36氪获悉，飞凯材料在互动平台回复投资者称，公司半导体材料可用于多种先进封装形式，其中包括Panel Level Packaging（PLP），但目前营收规模不大，对公司整体业绩影响较小。",
      "url": "https://36kr.com/newsflashes/3804576319806979?f=rss",
      "category": ""
    },
    {
      "title": "商络电子：暂未获海力士等存储厂商代理权",
      "date": "Mon, 11 May 2026 07:24:36 GMT",
      "summary": "36氪获悉，商络电子在互动平台表示，公司暂未取得海力士、西部数据、闪迪等存储厂商代理权；公司已获得铠侠存储代理权，并与国内主流存储厂商建立了长期稳定的授权分销关系。",
      "url": "https://36kr.com/newsflashes/3804565932088834?f=rss",
      "category": ""
    },
    {
      "title": "宝宝巴士旗下一公司减资90%",
      "date": "Mon, 11 May 2026 07:22:34 GMT",
      "summary": "36氪获悉，天眼查App显示，近日，学海拾贝（福建）科技有限公司发生工商变更，企业名称变更为学海拾贝（福州）科技有限公司，注册资本由1000万人民币减至100万人民币，同时，部分高管发生变更。该公司成立于2019年6月，法定代表人为唐光宇，经营范围含网络与信息安全软件开发、数字文化创意软件开发、信息技术咨询服务、信息系统运行维护服务、信息系统集成服务、数字内容制作服务、互联网销售等。股东信息显示，该公司由宝宝巴士股份有限公司全资持股。",
      "url": "https://36kr.com/newsflashes/3804563932192515?f=rss",
      "category": ""
    },
    {
      "title": "摩根大通策略师：下半年维持做多新兴市场股票立场",
      "date": "Mon, 11 May 2026 07:07:28 GMT",
      "summary": "摩根大通策略师表示，新兴市场股票有望在今年下半年迎来新一轮显著反弹，继续看好该类资产表现优于发达市场股票。由米斯拉夫・马泰伊卡领衔的策略师团队称，人工智能投资热潮仍在延续；而新兴市场相关标的估值更低、上行潜力更大。团队预判后续美债收益率走低、美元走弱，将利好新兴市场股市。预计伊朗局势趋于稳定，缓解市场对原油供应的担忧。新兴市场当前估值吸引力凸显：相对市盈率较发达市场处于历史极低水平，同时机构低配仓位仍处低位，资金流入节奏正在加快。（财联社）",
      "url": "https://36kr.com/newsflashes/3804549091958275?f=rss",
      "category": ""
    },
    {
      "title": "A股三大指数集体收涨，沪指突破4200点关口",
      "date": "Mon, 11 May 2026 07:01:11 GMT",
      "summary": "36氪获悉，A股三大指数集体收涨，沪指涨1.08%站上4200点，深成指涨2.16%，创业板指涨3.5%；工程机械、半导体、电脑硬件板块领涨，兴福电子、普冉股份涨停，江波龙涨超15%，三一重工涨超6%；贵金属、白酒、海运板块跌幅居前，国航远洋跌超6%，会稽山、中远海特跌超2%。",
      "url": "https://36kr.com/newsflashes/3804542924939011?f=rss",
      "category": ""
    },
    {
      "title": "理想整车研发负责人刘立国：说理想不重视技术，是大大的误解",
      "date": "Mon, 11 May 2026 06:59:01 GMT",
      "summary": "理想汽车整车电动研发高级副总裁 刘立国 文｜肖漫 编辑｜李勤 走过10年造车历程后，新势力阵营已经普遍从“轻盈”走向“厚重”。尤其是理想汽车，这家公司高呼成为“&nbsp;具身智能企业”，但也同时在垒高每一块整车技术能力。 尤其是过去4年，理想汽车几乎重构了底盘系统，联合供应商深度共创了底盘三大项：EMB刹车+800V主动悬架+线控转向。 理想在电池上也在进行自制布局，同时，在自身起家的增程技术上，理想也走到了自研自制阶段——其最新一代增程器，也即发动机，已经是理想汽车“自己生产”。 上述技术能力成果几乎都将集中体现在最新的旗舰车理想L9 Livis上。这意味着，新一代理想L9，也将是理想新一代技术能力的起点。 “从立项第一天起就定下目标，新一代L9的悬架和底盘技术必须成为整个行业的天花板。”理想&nbsp;L9 livis 在北京车展上第一次亮相时，李想说，仅20分钟的发布时间里，他花了一半的时间介绍底盘和悬架系统。 不久前，36氪访谈了理想整车电动研发负责人刘立国，其向36氪总结了理想一系列底盘技术布局背后的思考：用户体验的代际领先、智能化技术演进下的“小脑”需求，甚至对供应链安全",
      "url": "https://36kr.com/p/3804380633554696?f=rss",
      "category": ""
    }
  ],
  "status": "success",
  "error": null
}