{
  "source": "36氪",
  "source_url": "https://www.36kr.com/feed",
  "fetch_time": "2026-04-28T06:28:33.980Z",
  "articles": [
    {
      "title": "巴克莱一季度利润总额81.6亿英镑，高于预期",
      "date": "Tue, 28 Apr 2026 06:28:31 GMT",
      "summary": "巴克莱4月28日公布一季度股票业务收入11.2亿英镑，预估10.4亿英镑；一季度投行业务手续费收入7.54亿英镑，预估6.82亿英镑；一季度利润总额81.6亿英镑，预估81.1亿英镑；一季度净利息收入37.4亿英镑，预估38.3亿英镑；第一季度税前利润28.1亿英镑，预估28.5亿英镑。（界面）",
      "url": "https://36kr.com/newsflashes/3786108294650880?f=rss",
      "category": ""
    },
    {
      "title": "两部门：引导算力企业、模型企业、数据企业和应用开发企业组建“模数共振”创新联合体",
      "date": "Tue, 28 Apr 2026 06:26:36 GMT",
      "summary": "36氪获悉，工业和信息化部办公厅、国家数据局综合司发布关于联合实施2026年“模数共振”行动的通知，其中指出，围绕所选择的重点行业，引导算力企业、模型企业、数据企业和应用开发企业组建“模数共振”创新联合体（对于所选择的重点行业，每行业打造不少于1个），支持联合体与“模数共振”空间协作联动，共同开展模型研制、软硬适配、数据处理、应用方案设计与开发。组织联合体强化行业级、全栈式解决方案研发和应用，打造人工智能赋能行业“样板间”。",
      "url": "https://36kr.com/newsflashes/3786106417732615?f=rss",
      "category": ""
    },
    {
      "title": "英国石油一季度调整后净利润32亿美元，高于预期",
      "date": "Tue, 28 Apr 2026 06:22:19 GMT",
      "summary": "英国石油公布一季度调整后净利润32.0亿美元，上年同期13.8亿美元，预估26.4亿美元；调整后息税前利润62.7亿美元，同比增加40%，预估57.9亿美元。（财联社）",
      "url": "https://36kr.com/newsflashes/3786102194314245?f=rss",
      "category": ""
    },
    {
      "title": "bp一季度调整后净利润32亿美元，高于预期",
      "date": "Tue, 28 Apr 2026 06:14:01 GMT",
      "summary": "bp公布一季度调整后净利润32.0亿美元，上年同期13.8亿美元，预估26.4亿美元；调整后息税前利润62.7亿美元，同比增加40%，预估57.9亿美元。（界面）",
      "url": "https://36kr.com/newsflashes/3786094039358473?f=rss",
      "category": ""
    },
    {
      "title": "格力电器：已具备做“人形机器人”的能力",
      "date": "Tue, 28 Apr 2026 06:10:50 GMT",
      "summary": "格力电器CMO朱磊表示，目前公司已具备做出“人形机器人”的能力，所有机器人零部件都可以实现自研自产。格力累计投入使用的自主研制的工业机器人达到2000余台，实现生产效率提升80%。（21财经）",
      "url": "https://36kr.com/newsflashes/3786090907278595?f=rss",
      "category": ""
    },
    {
      "title": "恒生科技指数跌超2%",
      "date": "Tue, 28 Apr 2026 06:03:09 GMT",
      "summary": "36氪获悉，港股午后震荡走低，恒生科技指数跌超2%，恒生指数跌超1%。",
      "url": "https://36kr.com/newsflashes/3786083355843841?f=rss",
      "category": ""
    }
  ],
  "status": "success",
  "error": null
}