{
  "source": "36氪",
  "source_url": "https://www.36kr.com/feed",
  "fetch_time": "2026-06-30T10:49:17.173Z",
  "articles": [
    {
      "title": "国家新闻出版署公布2026年6月份国产网络游戏审批信息，共163款游戏获批",
      "date": "Tue, 30 Jun 2026 10:48:12 GMT",
      "summary": "36氪获悉，国家新闻出版署公布2026年6月份国产网络游戏审批信息，共163款游戏获批。",
      "url": "https://36kr.com/newsflashes/3875544971259904?f=rss",
      "category": ""
    },
    {
      "title": "深科技：HBM技术尚处于研发阶段，预计短期内不会产生相关销售收入和利润",
      "date": "Tue, 30 Jun 2026 10:44:05 GMT",
      "summary": "36氪获悉，深科技公告，公司股票连续三个交易日收盘价格涨幅偏离值累计超过20%，属于股票交易异常波动。公司半导体封测业务主要从事高端存储芯片的封装与测试，产品包括DRAM、NANDFLASH以及嵌入式存储芯片，并持续密切关注行业发展动态和前沿技术的发展趋势，公司HBM技术尚处于研发阶段，预计短期内不会产生相关销售收入和利润。公司股票价格近期涨幅较大，自6月16日至6月30日累计涨幅达57.64%，可能存在短期快速上涨后下跌的风险。",
      "url": "https://36kr.com/newsflashes/3875540915351558?f=rss",
      "category": ""
    },
    {
      "title": "彩虹股份：目前没有产品进入半导体封装相关领域的测试",
      "date": "Tue, 30 Jun 2026 10:38:35 GMT",
      "summary": "36氪获悉，彩虹股份公告，公司关注到近期市场对基板玻璃在半导体封装领域应用的关注度持续提升。目前，公司产品为显示用基板玻璃，产品主要客户为液晶面板厂商。公司将依托基板玻璃制造技术优势，逐步开展基板玻璃新应用调研，目前尚处于研发阶段，没有产品进入半导体封装相关领域的测试，未来相关业务的推进也存在不确定性，公司提醒广大投资者注意市场交易风险。",
      "url": "https://36kr.com/newsflashes/3875535505125634?f=rss",
      "category": ""
    },
    {
      "title": "数据港：公司拟授权管理层在不超过13亿元的额度内进行采购服务器及配套设备",
      "date": "Tue, 30 Jun 2026 10:37:15 GMT",
      "summary": "36氪获悉，数据港公告，公司董事会审议通过授权管理层在不超过13亿元额度内采购服务器及其配套设备，有效期至2026年年度董事会召开之日止。本次授权旨在推动“双轮驱动”战略落地，快速响应市场变化，但存在采购额度未足额使用、供应链风险及项目落地不确定性等风险。",
      "url": "https://36kr.com/newsflashes/3875534197092615?f=rss",
      "category": ""
    },
    {
      "title": "兴业银锡：拟收购Atlas Tin SAS 25%股权实现全资控股",
      "date": "Tue, 30 Jun 2026 10:34:46 GMT",
      "summary": "36氪获悉，兴业银锡公告，公司拟通过海外新设子公司收购丰田通商株式会社和日铁矿业株式会社合计持有的Atlas Tin SAS 25%股权，总对价2311.36万美元。交易完成后，公司将间接持有目标公司100%股权，实现对Achmmach锡矿项目的全资控股，旨在简化治理结构、提升决策效率，最大化释放锡矿资产价值。",
      "url": "https://36kr.com/newsflashes/3875531763233024?f=rss",
      "category": ""
    },
    {
      "title": "深中华A：黄金珠宝业务收入占总营业收入的比重为99%以上，目前已没有开展锂电池材料业务",
      "date": "Tue, 30 Jun 2026 10:32:51 GMT",
      "summary": "36氪获悉，深中华A公告，近期公司经营情况正常，内外部经营环境未发生重大变化。公司目前主要经营业务为黄金珠宝业务，黄金珠宝业务收入占总营业收入的比重为99%以上，自行车及其他业务收入占总营业收入的比重已不足1%，目前已没有开展锂电池材料业务。",
      "url": "https://36kr.com/newsflashes/3875529869668612?f=rss",
      "category": ""
    }
  ],
  "status": "success",
  "error": null
}